duckduckgoose/__init__.py
duckduckgoose-1.0.1.dist-info/METADATA
duckduckgoose-1.0.1.dist-info/WHEEL
duckduckgoose-1.0.1.dist-info/top_level.txt
duckduckgoose-1.0.1.dist-info/RECORD
