Metadata-Version: 2.1
Name: duckduckgoose
Version: 1.0.1
Summary: Client library for the DuckDuckGoose/DeepDetector API
Author-email: DuckDuckGoose <info@duckduckgoose.nl>
Project-URL: Homepage, https://deepdetector.docs.duckduckgoose.ai/
Keywords: deepfake,api,detection
Classifier: Programming Language :: Python
Classifier: Programming Language :: Python :: 3
Classifier: License :: OSI Approved :: Apache Software License
Requires-Python: >=3.5
Requires-Dist: ubiops
